Metadata-Version: 2.4
Name: adafruit-circuitpython-ina23x
Version: 1.0.1
Summary: CircuitPython driver for the INA237 and INA238 DC Current Voltage Power Monitor
Author-email: Adafruit Industries <circuitpython@adafruit.com>
License: MIT
Project-URL: Homepage, https://github.com/adafruit/Adafruit_CircuitPython_INA23x
Keywords: adafruit,blinka,circuitpython,micropython,ina23x,INA237,,INA238,,power,monitor
Classifier: Intended Audience :: Developers
Classifier: Topic :: Software Development :: Libraries
Classifier: Topic :: Software Development :: Embedded Systems
Classifier: Topic :: System :: Hardware
Classifier: License :: OSI Approved :: MIT License
Classifier: Programming Language :: Python :: 3
License-File: LICENSE
Requires-Dist: Adafruit-Blinka
Requires-Dist: adafruit-circuitpython-busdevice
Requires-Dist: adafruit-circuitpython-register
Requires-Dist: adafruit-circuitpython-ina228
Provides-Extra: optional
Dynamic: license-file
